AUTHORS
CHANGES.rst
LICENSE
MANIFEST.in
Makefile
README.rst
pytest.ini
setup.py
tox.ini
PyLink.egg-info/PKG-INFO
PyLink.egg-info/SOURCES.txt
PyLink.egg-info/dependency_links.txt
PyLink.egg-info/not-zip-safe
PyLink.egg-info/requires.txt
PyLink.egg-info/top_level.txt
pylink/__init__.py
pylink/compat.py
pylink/link.py
pylink/logger.py
pylink/test_links.py